{
    "AX": {
        "error": 0.05694107419258082, 
        "fit": "average_SEM", 
        "value": -0.016591042497020682
    }, 
    "CDD": {
        "error": 0.000165255757253999, 
        "fit": "average_SEM", 
        "value": 0.00011001272996509215
    }, 
    "H1": {
        "error": 0.10828007659142587, 
        "fit": "average_SEM", 
        "value": -0.009169303623881813
    }, 
    "H2": {
        "error": 0.11871571044184358, 
        "fit": "average_SEM", 
        "value": -0.018617459239127734
    }, 
    "L1": {
        "error": 0.11483849361951948, 
        "fit": "average_SEM", 
        "value": -0.08254945296260606
    }, 
    "L2": {
        "error": 0.14372913675880886, 
        "fit": "average_SEM", 
        "value": -0.029594666075718125
    }
}